sage_peptide_ambiguity_annotator/__init__.py
sage_peptide_ambiguity_annotator/main.py
sage_peptide_ambiguity_annotator-1.0.1.dist-info/licenses/LICENSE
sage_peptide_ambiguity_annotator-1.0.1.dist-info/METADATA
sage_peptide_ambiguity_annotator-1.0.1.dist-info/WHEEL
sage_peptide_ambiguity_annotator-1.0.1.dist-info/entry_points.txt
sage_peptide_ambiguity_annotator-1.0.1.dist-info/top_level.txt
sage_peptide_ambiguity_annotator-1.0.1.dist-info/RECORD
