Metadata-Version: 2.4
Name: sage-peptide-ambiguity-annotator
Version: 1.0.1
Summary: Annotate peptide spectrum matches (PSMs) from Sage with ambiguity information
Author-email: Patrick Garrett <pgarrett@scripps.edu>
License: MIT
Project-URL: Homepage, https://github.com/pgarrett-scripps/SagePeptideAmbiguityAnnotator
Project-URL: Bug Tracker, https://github.com/pgarrett-scripps/SagePeptideAmbiguityAnnotator/issues
Classifier: Programming Language :: Python :: 3
Classifier: License :: OSI Approved :: MIT License
Classifier: Operating System :: OS Independent
Classifier: Topic :: Scientific/Engineering :: Bio-Informatics
Requires-Python: >=3.9
License-File: LICENSE
Requires-Dist: pandas
Requires-Dist: fastparquet
Requires-Dist: peptacular==2.5.0
Dynamic: license-file
